nixi/__init__.py
nixi/dummy.py
nixie-0.1.0.dist-info/METADATA
nixie-0.1.0.dist-info/WHEEL
nixie-0.1.0.dist-info/top_level.txt
nixie-0.1.0.dist-info/RECORD
