Metadata-Version: 2.4
Name: nixie
Version: 0.1.0
Summary: Add your description here
Requires-Python: >=3.11
Requires-Dist: nixtla>=0.7.0
